{"time":1695812656,"ip":"2804:47c:530:6c00:8cc0:d352:4fa5:497","country":"BR","os":"unknown","isp":"InNET Ponto Com Ltda.","ua":"WhatsApp\/2.23.20.0","reason":["os"],"subs":{"is_ad_landing_page":"1","utm_source":"copy_link","utm_campaign":"client_share","utm_medium":"android","share_iid":"7282707298400945926","share_link_id":"a301d5c6-0b5d-4536-8489-79a6eecd209d","share_app_id":"1233","ugbiz_name":"UNKNOWN","ug_btm":"b2001,b5836","timestamp":"1695812625","user_id":"7170698097319298053","sec_user_id":"MS4wLjABAAAAV7f2QHSu2PmTa3GFXNFc0WhAntyZW4YF_1tMaKU8zOPRpKqXUnqq-mE4SNF3co8B","social_share_type":"4","checksum":"c85befde9904a9d87bed30c2da3909b0b6f8c50d1ed140d868d61f0369a2ec7b"},"_id":1245}