{"subid":"6503b6f868eb6","time":1694742264,"ip":"2804:f84:7:fbf4:b476:b550:c242:dc3","country":"BR","os":"iOS","isp":"MGP TELECOM","ua":"Mozilla\/5.0 (iPhone; CPU iPhone OS 15_7_8 like Mac OS X) AppleWebKit\/605.1.15 (KHTML  like Gecko) Mobile\/15E148 musical_ly_31.1.0 JsSdk\/2.0 NetType\/WIFI Channel\/App Store ByteLocale\/pt Region\/BR RevealType\/Dialog isDarkMode\/1 WKWebView\/1 BytedanceWebview\/d8a21c6 FalconTag\/880857BC-7642-47A8-8993-5A475E7F9E3C","subs":[],"preland":"unknown","land":"avaliador\/pv\/1-inicio","_id":10341}