{"subid":"650b3af24d459","time":1695234802,"ip":"177.74.184.228","country":"BR","os":"iOS","isp":"SKYNET TELECOMUNICACOES EIRELI","ua":"Mozilla\/5.0 (iPhone; CPU iPhone OS 16_6 like Mac OS X) AppleWebKit\/605.1.15 (KHTML  like Gecko) Mobile\/15E148 musical_ly_31.1.0 JsSdk\/2.0 NetType\/WIFI Channel\/App Store ByteLocale\/pt Region\/BR RevealType\/Dialog isDarkMode\/1 WKWebView\/1 BytedanceWebview\/d8a21c6 FalconTag\/BCD836D5-6123-4AEA-A00B-B4AB00759F84","subs":[],"preland":"unknown","land":"avaliador\/pv\/1-inicio","_id":12062}