{"subid":"64e6b8f252306","time":1692842226,"ip":"2804:431:c7c5:8fa8:1059:aaf2:9775:1162","country":"BR","os":"iOS","isp":"TELEFONICA BRASIL S.A","ua":"Mozilla\/5.0 (iPhone; CPU iPhone OS 16_4_1 like Mac OS X) AppleWebKit\/605.1.15 (KHTML  like Gecko) Mobile\/15E148 BytedanceWebview\/d8a21c6 musical_ly_30.7.0 JsSdk\/2.0 NetType\/WIFI Channel\/App Store ByteLocale\/pt Region\/BR FalconTag\/A58C3CD5-17A7-4B3B-910C-6F94B6540A79 TTP_H5_URLPROTOCOL","subs":[],"preland":"unknown","land":"avaliadoroferta\/1-3","_id":1241}