{"subid":"650b6cac85996","time":1695247532,"ip":"2804:30c:226f:c100:a1ba:733a:d98:a0d0","country":"BR","os":"iOS","isp":"Unifique Telecomunicacoes SA","ua":"Mozilla\/5.0 (iPhone; CPU iPhone OS 16_6_1 like Mac OS X) AppleWebKit\/605.1.15 (KHTML  like Gecko) Mobile\/15E148 musical_ly_31.2.0 JsSdk\/2.0 NetType\/WIFI Channel\/App Store ByteLocale\/pt Region\/BR RevealType\/Dialog isDarkMode\/0 WKWebView\/1 BytedanceWebview\/d8a21c6 FalconTag\/73B8A805-F01E-4464-8B43-CE3C6E8CD191","subs":[],"preland":"unknown","land":"avaliador\/pv\/1-inicio","_id":12561}