{"subid":"650b83c87a0d6","time":1695253448,"ip":"179.34.94.253","country":"BR","os":"iOS","isp":"TIM SA","ua":"Mozilla\/5.0 (iPhone; CPU iPhone OS 16_6_1 like Mac OS X) AppleWebKit\/605.1.15 (KHTML  like Gecko) Mobile\/15E148 musical_ly_31.2.0 JsSdk\/2.0 NetType\/WIFI Channel\/App Store ByteLocale\/pt Region\/BR RevealType\/Dialog isDarkMode\/0 WKWebView\/1 BytedanceWebview\/d8a21c6 FalconTag\/C44D0FB8-1CC2-4E57-A7A1-170ECCAC4431","subs":[],"preland":"unknown","land":"avaliador\/pv\/1-inicio","_id":13268}