{"subid":"650b913b0c964","time":1695256891,"ip":"2804:b10:caff:4100:71b4:62c5:8019:a7a2","country":"BR","os":"iOS","isp":"ISOTELCO LTDA","ua":"Mozilla\/5.0 (iPhone; CPU iPhone OS 16_6_1 like Mac OS X) AppleWebKit\/605.1.15 (KHTML  like Gecko) Mobile\/15E148 musical_ly_31.2.0 JsSdk\/2.0 NetType\/WIFI Channel\/App Store ByteLocale\/pt Region\/BR RevealType\/Dialog isDarkMode\/0 WKWebView\/1 BytedanceWebview\/d8a21c6 FalconTag\/4402B32F-D3EA-4504-9935-389F7F2DA119","subs":[],"preland":"unknown","land":"avaliador\/pv\/1-inicio","_id":13658}