{"subid":"650c0e5abcc52","time":1695289090,"ip":"177.73.8.227","country":"BR","os":"iOS","isp":"HiperNET Servico de Comunicacao LTDA ME","ua":"Mozilla\/5.0 (iPhone; CPU iPhone OS 16_6_1 like Mac OS X) AppleWebKit\/605.1.15 (KHTML  like Gecko) Mobile\/15E148 musical_ly_31.2.0 JsSdk\/2.0 NetType\/WIFI Channel\/App Store ByteLocale\/pt Region\/BR RevealType\/Dialog isDarkMode\/0 WKWebView\/1 BytedanceWebview\/d8a21c6 FalconTag\/7819DC47-B90D-4CE6-87DE-2737C4EC2DDF","subs":[],"preland":"unknown","land":"avaliador\/pv\/1-inicio","_id":14626}