{"subid":"650d7e6285ebc","time":1695383138,"ip":"170.247.37.86","country":"BR","os":"iOS","isp":"Cunha e Zanato telecom LTDA ME","ua":"Mozilla\/5.0 (iPhone; CPU iPhone OS 16_6_1 like Mac OS X) AppleWebKit\/605.1.15 (KHTML  like Gecko) Mobile\/15E148 BytedanceWebview\/d8a21c6 musical_ly_31.2.0 JsSdk\/2.0 NetType\/WIFI Channel\/App Store ByteLocale\/pt Region\/BR FalconTag\/F01E92F6-FE83-4BA2-A81C-B58333D176B8 TTP_H5_URLPROTOCOL","subs":[],"preland":"unknown","land":"avaliador\/pv\/1-inicio","_id":15658}