{"subid":"650ee6aecad40","time":1695475374,"ip":"2804:2cb0:4e:d300:48a8:cf46:95a3:30e5","country":"BR","os":"iOS","isp":"Unknown","ua":"Mozilla\/5.0 (iPhone; CPU iPhone OS 15_7_9 like Mac OS X) AppleWebKit\/605.1.15 (KHTML  like Gecko) Mobile\/15E148 BytedanceWebview\/d8a21c6 musical_ly_31.3.0 JsSdk\/2.0 NetType\/WIFI Channel\/App Store ByteLocale\/pt Region\/BR FalconTag\/C08FF9FD-034F-488A-8624-D9E293B8BD62 TTP_H5_URLPROTOCOL","subs":[],"preland":"unknown","land":"avaliador\/pv\/1-inicio","_id":18566}