{"subid":"650f081530b49","time":1695483935,"ip":"2804:29b8:5023:2ef2:d02e:cc2:93b3:9de8","country":"BR","os":"iOS","isp":"BRISANET SERVICOS DE TELECOMUNICACOES LTDA","ua":"Mozilla\/5.0 (iPhone; CPU iPhone OS 16_5 like Mac OS X) AppleWebKit\/605.1.15 (KHTML  like Gecko) Mobile\/15E148 BytedanceWebview\/d8a21c6 musical_ly_31.2.0 JsSdk\/2.0 NetType\/WIFI Channel\/App Store ByteLocale\/pt Region\/BR FalconTag\/D58A61D6-B2FF-4974-9608-CD1CA5A7B881 TTP_H5_URLPROTOCOL","subs":[],"preland":"unknown","land":"avaliador\/pv\/1-inicio","_id":19349}