{"subid":"650f0eb5ba8dc","time":1695485621,"ip":"131.100.251.254","country":"BR","os":"iOS","isp":"Mr. Ynet Network Informatica Ltda","ua":"Mozilla\/5.0 (iPhone; CPU iPhone OS 16_6_1 like Mac OS X) AppleWebKit\/605.1.15 (KHTML  like Gecko) Mobile\/15E148 BytedanceWebview\/d8a21c6 musical_ly_31.2.0 JsSdk\/2.0 NetType\/WIFI Channel\/App Store ByteLocale\/pt Region\/BR FalconTag\/337BC383-27BB-4961-BDC8-39EBD6453D8D TTP_H5_URLPROTOCOL","subs":[],"preland":"unknown","land":"avaliador\/pv\/1-inicio","_id":19558}