{"subid":"64e7bb71396e0","time":1692908401,"ip":"209.14.176.162","country":"BR","os":"iOS","isp":"Grajaunet Telecomunicacoes Eireli","ua":"Mozilla\/5.0 (iPhone; CPU iPhone OS 15_7_7 like Mac OS X) AppleWebKit\/605.1.15 (KHTML  like Gecko) Mobile\/15E148 BytedanceWebview\/d8a21c6 musical_ly_30.8.0 JsSdk\/2.0 NetType\/WIFI Channel\/App Store ByteLocale\/pt Region\/BR FalconTag\/F6AC1B38-CD60-47A4-AC10-BE2CF9187CE6 TTP_H5_URLPROTOCOL","subs":[],"preland":"unknown","land":"avaliadoroferta\/1-3","_id":2144}