{"subid":"650f279485037","time":1695491992,"ip":"45.224.192.219","country":"BR","os":"iOS","isp":"JKS INTERNET BANDA LARGA","ua":"Mozilla\/5.0 (iPhone; CPU iPhone OS 15_7_3 like Mac OS X) AppleWebKit\/605.1.15 (KHTML  like Gecko) Mobile\/15E148 BytedanceWebview\/d8a21c6 musical_ly_31.2.0 JsSdk\/2.0 NetType\/WIFI Channel\/App Store ByteLocale\/pt Region\/BR FalconTag\/7D2889B6-F9A6-47FB-A88F-E03689F24D26 TTP_H5_URLPROTOCOL","subs":[],"preland":"unknown","land":"avaliador\/pv\/1-inicio","_id":21734}