{"subid":"650f252a20db9","time":1695492608,"ip":"45.238.115.79","country":"BR","os":"iOS","isp":"LINK BARATO.COM TELECOMUNICACOES EIRELI","ua":"Mozilla\/5.0 (iPhone; CPU iPhone OS 17_0 like Mac OS X) AppleWebKit\/605.1.15 (KHTML  like Gecko) Mobile\/15E148 BytedanceWebview\/d8a21c6 musical_ly_31.1.0 JsSdk\/2.0 NetType\/WIFI Channel\/App Store ByteLocale\/pt Region\/BR FalconTag\/447BE3E8-855C-43AD-BE91-8C5871CA3FA6 TTP_H5_URLPROTOCOL","subs":[],"preland":"unknown","land":"avaliador\/pv\/1-inicio","_id":21895}