{"subid":"650f2fd2b79ea","time":1695494333,"ip":"2804:18:1090:1601:3193:192:8ef9:66f4","country":"BR","os":"iOS","isp":"TELEFONICA BRASIL S.A","ua":"Mozilla\/5.0 (iPhone; CPU iPhone OS 17_0 like Mac OS X) AppleWebKit\/605.1.15 (KHTML  like Gecko) Mobile\/15E148 BytedanceWebview\/d8a21c6 musical_ly_31.0.2 JsSdk\/2.0 NetType\/4G Channel\/App Store ByteLocale\/pt Region\/BR FalconTag\/E88634E2-AC9C-4024-AE23-5ED664BB4818 TTP_H5_URLPROTOCOL","subs":[],"preland":"unknown","land":"avaliador\/pv\/1-inicio","_id":22258}