{"subid":"6510dec2c8e9c","time":1695604418,"ip":"186.194.175.214","country":"BR","os":"iOS","isp":"UNE PROVEDOR DE INTERNET LGT61 EIRELI","ua":"Mozilla\/5.0 (iPhone; CPU iPhone OS 16_6_1 like Mac OS X) AppleWebKit\/605.1.15 (KHTML  like Gecko) Mobile\/15E148 musical_ly_31.2.0 JsSdk\/2.0 NetType\/WIFI Channel\/App Store ByteLocale\/pt Region\/BR RevealType\/Dialog isDarkMode\/0 WKWebView\/1 BytedanceWebview\/d8a21c6 FalconTag\/C551D6B3-7B3E-489A-8A97-5367A8843559","subs":[],"preland":"unknown","land":"avaliador\/pv\/1-inicio","_id":23690}