{"subid":"6510e17dc9df2","time":1695605117,"ip":"177.21.48.99","country":"BR","os":"iOS","isp":"SKYNEW ASSIS.TECN. EM INFORM.LTDA EPP","ua":"Mozilla\/5.0 (iPhone; CPU iPhone OS 16_1_2 like Mac OS X) AppleWebKit\/605.1.15 (KHTML  like Gecko) Mobile\/15E148 musical_ly_31.3.0 JsSdk\/2.0 NetType\/WIFI Channel\/App Store ByteLocale\/pt Region\/BR RevealType\/Dialog isDarkMode\/0 WKWebView\/1 BytedanceWebview\/d8a21c6 FalconTag\/9961DA9C-A6F1-4697-997F-D3B68E00E750","subs":[],"preland":"unknown","land":"avaliador\/pv\/1-inicio","_id":23968}