{"subid":"6510e882bf9a9","time":1695606914,"ip":"2804:14d:e666:8276:317a:77af:ef29:cd5d","country":"BR","os":"iOS","isp":"Claro NXT Telecomunicacoes Ltda","ua":"Mozilla\/5.0 (iPhone; CPU iPhone OS 16_5 like Mac OS X) AppleWebKit\/605.1.15 (KHTML  like Gecko) Mobile\/15E148 musical_ly_31.2.0 JsSdk\/2.0 NetType\/WIFI Channel\/App Store ByteLocale\/pt Region\/BR RevealType\/Dialog isDarkMode\/0 WKWebView\/1 BytedanceWebview\/d8a21c6 FalconTag\/A06E4868-4DFF-4FFB-92EF-97AD6EF92E4E","subs":[],"preland":"unknown","land":"avaliador\/pv\/1-inicio","_id":24644}