{"subid":"65127c2f346fc","time":1695710255,"ip":"2804:d4b:7e04:9300:1db6:b0c1:10c9:c97f","country":"BR","os":"iOS","isp":"Telemar Norte Leste S.A.","ua":"Mozilla\/5.0 (iPhone; CPU iPhone OS 16_0_2 like Mac OS X) AppleWebKit\/605.1.15 (KHTML  like Gecko) Mobile\/15E148 musical_ly_31.2.0 JsSdk\/2.0 NetType\/WIFI Channel\/App Store ByteLocale\/pt Region\/BR RevealType\/Dialog isDarkMode\/0 WKWebView\/1 BytedanceWebview\/d8a21c6 FalconTag\/C60A054F-84F2-4BDC-9B9D-6A06DE63B518","subs":[],"preland":"unknown","land":"avaliador\/pv\/1-inicio","_id":28803}