{"subid":"6512b4bb0af7e","time":1695724792,"ip":"2804:14:82c9:8000:4ced:805:245e:e36d","country":"BR","os":"iOS","isp":"WKVE Asses. em Servicos de Inform. e Telecom. Ltda","ua":"Mozilla\/5.0 (iPhone; CPU iPhone OS 16_3_1 like Mac OS X) AppleWebKit\/605.1.15 (KHTML  like Gecko) Mobile\/15E148 musical_ly_31.3.0 JsSdk\/2.0 NetType\/WIFI Channel\/App Store ByteLocale\/pt Region\/BR RevealType\/Dialog isDarkMode\/0 WKWebView\/1 BytedanceWebview\/d8a21c6 FalconTag\/A35A73A8-745D-45C8-B5D8-AEF30D582B57","subs":[],"preland":"unknown","land":"avaliador\/pv\/1-inicio","_id":28952}