{"subid":"65135f19e20f6","time":1695768345,"ip":"170.0.107.33","country":"BR","os":"iOS","isp":"NETWORK SOLUCOES INTERNET LTDA","ua":"Mozilla\/5.0 (iPhone; CPU iPhone OS 16_3_1 like Mac OS X) AppleWebKit\/605.1.15 (KHTML  like Gecko) Mobile\/15E148 musical_ly_31.2.0 JsSdk\/2.0 NetType\/WIFI Channel\/App Store ByteLocale\/pt Region\/BR RevealType\/Dialog isDarkMode\/0 WKWebView\/1 BytedanceWebview\/d8a21c6 FalconTag\/ACFCB070-E7F6-4529-A9D2-5B79964B8647","subs":[],"preland":"unknown","land":"avaliador\/pv\/1-inicio","_id":31084}