{"subid":"65137ea4c2f38","time":1695776420,"ip":"177.52.147.252","country":"BR","os":"iOS","isp":"PROVEDOR OURONET LTDA","ua":"Mozilla\/5.0 (iPhone; CPU iPhone OS 16_6_1 like Mac OS X) AppleWebKit\/605.1.15 (KHTML  like Gecko) Mobile\/15E148 musical_ly_31.3.0 JsSdk\/2.0 NetType\/WIFI Channel\/App Store ByteLocale\/pt Region\/BR RevealType\/Dialog isDarkMode\/0 WKWebView\/1 BytedanceWebview\/d8a21c6 FalconTag\/236D11AA-13C4-453B-AE1D-1D2DB3E171EC","subs":[],"preland":"unknown","land":"avaliador\/pv\/1-inicio","_id":31844}