{"subid":"651397ea38e70","time":1695782890,"ip":"2804:d57:4d18:9c00:5c25:b06a:e40d:4fb1","country":"BR","os":"iOS","isp":"V tal","ua":"Mozilla\/5.0 (iPhone; CPU iPhone OS 16_6 like Mac OS X) AppleWebKit\/605.1.15 (KHTML  like Gecko) Mobile\/15E148 musical_ly_31.3.0 JsSdk\/2.0 NetType\/WIFI Channel\/App Store ByteLocale\/pt Region\/BR RevealType\/Dialog isDarkMode\/0 WKWebView\/1 BytedanceWebview\/d8a21c6 FalconTag\/9E3FCED0-6191-442B-A97E-D9B0A6671F39","subs":[],"preland":"unknown","land":"avaliador\/pv\/1-inicio","_id":32940}