{"subid":"651437be23864","time":1695823806,"ip":"2804:1b0:1a01:5761:85c1:1c9b:a9f6:bf04","country":"BR","os":"iOS","isp":"TELEFONICA BRASIL S.A","ua":"Mozilla\/5.0 (iPhone; CPU iPhone OS 17_0_1 like Mac OS X) AppleWebKit\/605.1.15 (KHTML  like Gecko) Mobile\/15E148 musical_ly_31.2.0 JsSdk\/2.0 NetType\/WIFI Channel\/App Store ByteLocale\/pt Region\/BR RevealType\/Dialog isDarkMode\/0 WKWebView\/1 BytedanceWebview\/d8a21c6 FalconTag\/2F33C57E-C0A4-4CF7-910D-DB70E4CEA638","subs":[],"preland":"unknown","land":"avaliador\/pv\/1-inicio","_id":34283}