{"subid":"65143cee71d0a","time":1695825134,"ip":"2804:2538:804:c200:e068:a972:2983:6197","country":"BR","os":"iOS","isp":"MICRON LINE SERVICOS DE INFORMATICA LTDA - ME","ua":"Mozilla\/5.0 (iPhone; CPU iPhone OS 17_0_1 like Mac OS X) AppleWebKit\/605.1.15 (KHTML  like Gecko) Mobile\/15E148 musical_ly_31.3.0 JsSdk\/2.0 NetType\/WIFI Channel\/App Store ByteLocale\/pt Region\/BR isDarkMode\/0 WKWebView\/1 RevealType\/Dialog BytedanceWebview\/d8a21c6 FalconTag\/22D07C56-F528-4916-9690-4F4151DCFB74","subs":[],"preland":"unknown","land":"avaliador\/pv\/1-inicio","_id":34452}