{"subid":"651456dda88ae","time":1695831773,"ip":"186.226.49.87","country":"BR","os":"iOS","isp":"OesteLine Informatica Ltda.","ua":"Mozilla\/5.0 (iPhone; CPU iPhone OS 16_7 like Mac OS X) AppleWebKit\/605.1.15 (KHTML  like Gecko) Mobile\/15E148 musical_ly_31.3.0 JsSdk\/2.0 NetType\/WIFI Channel\/App Store ByteLocale\/pt Region\/BR RevealType\/Dialog isDarkMode\/1 WKWebView\/1 BytedanceWebview\/d8a21c6 FalconTag\/1ABEFAA6-D5B4-498F-89E6-F358A2FF3015","subs":[],"preland":"unknown","land":"avaliador\/pv\/1-inicio","_id":35094}