{"subid":"65147095170d6","time":1695838437,"ip":"2804:18:43:4a32:508a:2e9c:2270:3c74","country":"BR","os":"iOS","isp":"TELEFONICA BRASIL S.A","ua":"Mozilla\/5.0 (iPhone; CPU iPhone OS 16_6_1 like Mac OS X) AppleWebKit\/605.1.15 (KHTML  like Gecko) Mobile\/15E148 BytedanceWebview\/d8a21c6 musical_ly_31.3.0 JsSdk\/2.0 NetType\/WIFI Channel\/App Store ByteLocale\/pt Region\/BR FalconTag\/6689E6C1-F475-4FB4-ACE7-B5B0C41BD33C TTP_H5_URLPROTOCOL","subs":[],"preland":"unknown","land":"avaliador\/pv\/1-inicio","_id":35759}