{"subid":"6514820d8fc35","time":1695842829,"ip":"168.228.216.40","country":"BR","os":"iOS","isp":"ISI-AS","ua":"Mozilla\/5.0 (iPhone; CPU iPhone OS 16_6_1 like Mac OS X) AppleWebKit\/605.1.15 (KHTML  like Gecko) Mobile\/15E148 musical_ly_28.2.0 JsSdk\/2.0 NetType\/WIFI Channel\/App Store ByteLocale\/pt Region\/BR RevealType\/Dialog isDarkMode\/0 WKWebView\/1 BytedanceWebview\/d8a21c6 FalconTag\/C787673E-5D00-4CD0-A4A7-44873AAD0EA1","subs":[],"preland":"unknown","land":"avaliador\/pv\/1-inicio","_id":36396}