{"subid":"6514859d1b75a","time":1695843741,"ip":"2804:568:4ff:7600:a967:dbcd:de0e:5333","country":"BR","os":"iOS","isp":"TelecomDados Ltda","ua":"Mozilla\/5.0 (iPhone; CPU iPhone OS 17_0_1 like Mac OS X) AppleWebKit\/605.1.15 (KHTML  like Gecko) Mobile\/15E148 musical_ly_31.3.0 JsSdk\/2.0 NetType\/WIFI Channel\/App Store ByteLocale\/pt Region\/BR RevealType\/Dialog isDarkMode\/0 WKWebView\/1 BytedanceWebview\/d8a21c6 FalconTag\/DE2E3F43-8A95-4CE8-9A84-086675FB5FFD","subs":[],"preland":"unknown","land":"avaliador\/pv\/1-inicio","_id":36617}