{"subid":"651487aca52bf","time":1695844268,"ip":"168.0.226.252","country":"BR","os":"iOS","isp":"JOSE APARECIDO PEREIRA DA SILVA TELNET - ME","ua":"Mozilla\/5.0 (iPhone; CPU iPhone OS 16_6_1 like Mac OS X) AppleWebKit\/605.1.15 (KHTML  like Gecko) Mobile\/15E148 musical_ly_31.2.0 JsSdk\/2.0 NetType\/WIFI Channel\/App Store ByteLocale\/pt Region\/BR RevealType\/Dialog isDarkMode\/0 WKWebView\/1 BytedanceWebview\/d8a21c6 FalconTag\/40B6FA35-4D68-4A77-8DDE-FB1EA915D377","subs":[],"preland":"unknown","land":"avaliador\/pv\/1-inicio","_id":36689}