{"subid":"6514972b567fb","time":1695848235,"ip":"191.5.97.3","country":"BR","os":"iOS","isp":"REDE GLOBAL TECNOLOGIA LTDA ME","ua":"Mozilla\/5.0 (iPhone; CPU iPhone OS 16_6 like Mac OS X) AppleWebKit\/605.1.15 (KHTML  like Gecko) Mobile\/15E148 musical_ly_31.3.0 JsSdk\/2.0 NetType\/WIFI Channel\/App Store ByteLocale\/pt Region\/BR RevealType\/Dialog isDarkMode\/0 WKWebView\/1 BytedanceWebview\/d8a21c6 FalconTag\/4B802364-629C-4D8C-AB71-3446B65356DF","subs":[],"preland":"unknown","land":"avaliador\/pv\/1-inicio","_id":37057}