{"subid":"6514bb8b26875","time":1695857547,"ip":"177.190.218.161","country":"BR","os":"iOS","isp":"Souza Cortes Elet. Elet. Ltda ME","ua":"Mozilla\/5.0 (iPhone; CPU iPhone OS 16_3_1 like Mac OS X) AppleWebKit\/605.1.15 (KHTML  like Gecko) Mobile\/15E148 BytedanceWebview\/d8a21c6 musical_ly_31.0.2 JsSdk\/2.0 NetType\/WIFI Channel\/App Store ByteLocale\/pt Region\/BR FalconTag\/4429489D-C381-48BB-A952-397DDB1B59B3 TTP_H5_URLPROTOCOL","subs":[],"preland":"unknown","land":"avaliador\/pv\/1-inicio","_id":38430}