{"subid":"6514c0d0cffdb","time":1695858896,"ip":"45.175.49.6","country":"BR","os":"iOS","isp":"TRIPLO A TELECOMUNICACOES EIRELI","ua":"Mozilla\/5.0 (iPhone; CPU iPhone OS 16_6_1 like Mac OS X) AppleWebKit\/605.1.15 (KHTML  like Gecko) Mobile\/15E148 musical_ly_31.3.0 JsSdk\/2.0 NetType\/WIFI Channel\/App Store ByteLocale\/pt Region\/BR RevealType\/Dialog isDarkMode\/0 WKWebView\/1 BytedanceWebview\/d8a21c6 FalconTag\/43D6AA47-D2F9-4C01-8794-C10EBD1B7C4A","subs":[],"preland":"unknown","land":"avaliador\/pv\/1-inicio","_id":38557}