{"subid":"64edee56621d3","time":1693314646,"ip":"2804:1440:2068:e500:b1cd:527b:378c:37cb","country":"BR","os":"iOS","isp":"ILOGNET PROVEDOR","ua":"Mozilla\/5.0 (iPhone; CPU iPhone OS 15_7_8 like Mac OS X) AppleWebKit\/605.1.15 (KHTML  like Gecko) Mobile\/15E148 musical_ly_30.9.0 JsSdk\/2.0 NetType\/WIFI Channel\/App Store ByteLocale\/pt Region\/BR RevealType\/Dialog isDarkMode\/0 WKWebView\/1 BytedanceWebview\/d8a21c6 FalconTag\/72AE2ACD-3E51-476D-956E-6E8AE963C156","subs":[],"preland":"unknown","land":"avaliadoroferta\/1-3","_id":3968}