{"subid":"651ad4363e665","time":1696257078,"ip":"2804:7f4:c983:4e4c:31f3:edc0:7812:d68","country":"BR","os":"iOS","isp":"TELEFONICA BRASIL S.A","ua":"Mozilla\/5.0 (iPhone; CPU iPhone OS 17_0_1 like Mac OS X) AppleWebKit\/605.1.15 (KHTML  like Gecko) Mobile\/15E148 musical_ly_31.3.0 JsSdk\/2.0 NetType\/WIFI Channel\/App Store ByteLocale\/pt Region\/BR RevealType\/Dialog isDarkMode\/0 WKWebView\/1 BytedanceWebview\/d8a21c6 FalconTag\/64A07CC2-6116-4A71-B1ED-73838A952F42","subs":[],"preland":"unknown","land":"velhorico\/mvr-app1","_id":40124}