{"subid":"651ad41802438","time":1696257140,"ip":"138.0.24.226","country":"BR","os":"iOS","isp":"Erik Lucas Barbosa","ua":"Mozilla\/5.0 (iPhone; CPU iPhone OS 16_6_1 like Mac OS X) AppleWebKit\/605.1.15 (KHTML  like Gecko) Mobile\/15E148 musical_ly_31.3.0 JsSdk\/2.0 NetType\/WIFI Channel\/App Store ByteLocale\/pt Region\/BR RevealType\/Dialog isDarkMode\/0 WKWebView\/1 BytedanceWebview\/d8a21c6 FalconTag\/23CAAD5C-F67C-4C6E-8C01-B3D7E869D9B3","subs":[],"preland":"unknown","land":"velhorico\/mvr-app1","_id":40232}