{"subid":"651ad63255848","time":1696257586,"ip":"179.108.186.60","country":"BR","os":"iOS","isp":"Estrelar Web Servicos de Internet LTDA","ua":"Mozilla\/5.0 (iPhone; CPU iPhone OS 16_6_1 like Mac OS X) AppleWebKit\/605.1.15 (KHTML  like Gecko) Mobile\/15E148 musical_ly_31.3.0 JsSdk\/2.0 NetType\/WIFI Channel\/App Store ByteLocale\/pt Region\/BR RevealType\/Dialog isDarkMode\/0 WKWebView\/1 BytedanceWebview\/d8a21c6 FalconTag\/05F6FCBD-EE64-4C20-85DC-894FC0395141","subs":[],"preland":"unknown","land":"velhorico\/mvr-app1","_id":40831}