{"subid":"651ad523e5f8c","time":1696258015,"ip":"2804:14c:87:56f3:c58:a517:cc75:252d","country":"BR","os":"iOS","isp":"Claro NXT Telecomunicacoes Ltda","ua":"Mozilla\/5.0 (iPhone; CPU iPhone OS 16_3_1 like Mac OS X) AppleWebKit\/605.1.15 (KHTML  like Gecko) Mobile\/15E148 musical_ly_31.3.0 JsSdk\/2.0 NetType\/WIFI Channel\/App Store ByteLocale\/pt Region\/BR RevealType\/Dialog isDarkMode\/1 WKWebView\/1 BytedanceWebview\/d8a21c6 FalconTag\/096EAFCF-56CB-4A75-8000-0337C6541D66","subs":[],"preland":"unknown","land":"velhorico\/mvr-app1","_id":41154}