{"subid":"6521a9a3c5bd1","time":1696705046,"ip":"191.212.147.142","country":"BR","os":"iOS","isp":"Telemar Norte Leste S.A.","ua":"Mozilla\/5.0 (iPhone; CPU iPhone OS 15_5 like Mac OS X) AppleWebKit\/605.1.15 (KHTML  like Gecko) Mobile\/15E148 musical_ly_31.4.0 JsSdk\/2.0 NetType\/WIFI Channel\/App Store ByteLocale\/pt Region\/BR RevealType\/Dialog isDarkMode\/0 WKWebView\/1 BytedanceWebview\/d8a21c6 FalconTag\/5D2966F7-45D1-4BFB-8B60-64D1BC2DDD36","subs":[],"preland":"unknown","land":"velhorico\/mvr-app1","_id":42912}