{"subid":"6521ada7c45e9","time":1696705959,"ip":"2804:18:867:8db7:7daa:fcb8:c696:397","country":"BR","os":"iOS","isp":"TELEFONICA BRASIL S.A","ua":"Mozilla\/5.0 (iPhone; CPU iPhone OS 17_0_2 like Mac OS X) AppleWebKit\/605.1.15 (KHTML  like Gecko) Mobile\/15E148 musical_ly_31.3.0 JsSdk\/2.0 NetType\/WIFI Channel\/App Store ByteLocale\/pt Region\/BR RevealType\/Dialog isDarkMode\/0 WKWebView\/1 BytedanceWebview\/d8a21c6 FalconTag\/AE8462F3-F639-4CAA-89F9-C1564C86A949","subs":[],"preland":"unknown","land":"velhorico\/mvr-app1","_id":43354}