{"subid":"6521ae0810f86","time":1696706056,"ip":"2804:14c:6591:8861::9159","country":"BR","os":"iOS","isp":"Claro NXT Telecomunicacoes Ltda","ua":"Mozilla\/5.0 (iPhone; CPU iPhone OS 15_7_9 like Mac OS X) AppleWebKit\/605.1.15 (KHTML  like Gecko) Mobile\/15E148 musical_ly_31.4.0 JsSdk\/2.0 NetType\/WIFI Channel\/App Store ByteLocale\/pt Region\/BR RevealType\/Dialog isDarkMode\/0 WKWebView\/1 BytedanceWebview\/d8a21c6 FalconTag\/E39D0C93-CD8D-4DCE-9B95-1BFE8746E009","subs":[],"preland":"unknown","land":"velhorico\/mvr-app1","_id":43407}