{"subid":"64eeed53ad807","time":1693379923,"ip":"2804:1b3:c000:6e26:588:7cbe:8907:ba4f","country":"BR","os":"Android","isp":"TELEFONICA BRASIL S.A","ua":"Mozilla\/5.0 (Linux; Android 13; 2201116SG Build\/TKQ1.221114.001; wv) AppleWebKit\/537.36 (KHTML  like Gecko) Version\/4.0 Chrome\/115.0.5790.166 Mobile Safari\/537.36 trill_2023008040 JsSdk\/1.0 NetType\/WIFI Channel\/xiaomiglobal_int AppName\/musical_ly app_version\/30.8.4 ByteLocale\/pt-BR ByteFullLocale\/pt-BR Region\/BR BytedanceWebview\/d8a21c6","subs":[],"preland":"unknown","land":"avaliadoroferta\/1-3","_id":4355}