{"subid":"6521af8e90c31","time":1696706446,"ip":"2804:14c:4c7:a4d0:f513:c935:2d79:e53b","country":"BR","os":"iOS","isp":"Claro NXT Telecomunicacoes Ltda","ua":"Mozilla\/5.0 (iPhone; CPU iPhone OS 17_0_2 like Mac OS X) AppleWebKit\/605.1.15 (KHTML  like Gecko) Mobile\/15E148 musical_ly_31.3.0 JsSdk\/2.0 NetType\/WIFI Channel\/App Store ByteLocale\/pt Region\/BR RevealType\/Dialog isDarkMode\/0 WKWebView\/1 BytedanceWebview\/d8a21c6 FalconTag\/690548FB-1CA7-4709-A0E9-F7E9EECB6C96","subs":[],"preland":"unknown","land":"velhorico\/mvr-app1","_id":43608}