{"subid":"6521b73311d89","time":1696708403,"ip":"2804:d59:832a:b500:498d:81be:22c7:ff98","country":"BR","os":"iOS","isp":"V tal","ua":"Mozilla\/5.0 (iPhone; CPU iPhone OS 16_7 like Mac OS X) AppleWebKit\/605.1.15 (KHTML  like Gecko) Mobile\/15E148 BytedanceWebview\/d8a21c6 musical_ly_31.1.0 JsSdk\/2.0 NetType\/WIFI Channel\/App Store ByteLocale\/pt Region\/BR FalconTag\/2ED1E1A3-28DB-426C-95A2-9516B50CDC57 TTP_H5_URLPROTOCOL","subs":[],"preland":"unknown","land":"velhorico\/mvr-app1","_id":44258}