{"subid":"6521b74f1915b","time":1696708431,"ip":"177.12.101.136","country":"BR","os":"iOS","isp":"NETLINE TELECOM","ua":"Mozilla\/5.0 (iPhone; CPU iPhone OS 15_7_9 like Mac OS X) AppleWebKit\/605.1.15 (KHTML  like Gecko) Mobile\/15E148 musical_ly_31.3.0 JsSdk\/2.0 NetType\/WIFI Channel\/App Store ByteLocale\/pt Region\/BR RevealType\/Dialog isDarkMode\/1 WKWebView\/1 BytedanceWebview\/d8a21c6 FalconTag\/2CA5A574-101F-4CBB-9495-F99BB3D8A1F7","subs":[],"preland":"unknown","land":"velhorico\/mvr-app1","_id":44266}