{"subid":"6521ba30a5cb6","time":1696709168,"ip":"2804:388:e06d:9906:da5:2c07:d6bf:9c2a","country":"BR","os":"iOS","isp":"Claro SA","ua":"Mozilla\/5.0 (iPhone; CPU iPhone OS 16_6_1 like Mac OS X) AppleWebKit\/605.1.15 (KHTML  like Gecko) Mobile\/15E148 BytedanceWebview\/d8a21c6 musical_ly_31.3.0 JsSdk\/2.0 NetType\/4G Channel\/App Store ByteLocale\/pt Region\/BR FalconTag\/7B7C1339-E14D-4C62-B41A-04776C303A0D TTP_H5_URLPROTOCOL","subs":[],"preland":"unknown","land":"velhorico\/mvr-app1","_id":44578}