{"subid":"64ef36fa056e2","time":1693398778,"ip":"179.250.99.80","country":"BR","os":"iOS","isp":"TIM SA","ua":"Mozilla\/5.0 (iPhone; CPU iPhone OS 16_0_3 like Mac OS X) AppleWebKit\/605.1.15 (KHTML  like Gecko) Mobile\/15E148 musical_ly_30.8.0 JsSdk\/2.0 NetType\/WIFI Channel\/App Store ByteLocale\/pt Region\/BR RevealType\/Dialog isDarkMode\/0 WKWebView\/1 BytedanceWebview\/d8a21c6 FalconTag\/86F897CD-6B6D-4F99-9FC7-88E5ACF2DAE8","subs":[],"preland":"unknown","land":"avaliadoroferta\/1-3","_id":4547}