{"subid":"6521c2c013ef9","time":1696711360,"ip":"2804:868:d046:7040:345c:597d:47e8:13d7","country":"BR","os":"Android","isp":"Desktop Sigmanet Comunicacao Multimidia SA","ua":"Mozilla\/5.0 (Linux; Android 13; SM-A035M Build\/TP1A.220624.014; wv) AppleWebKit\/537.36 (KHTML  like Gecko) Version\/4.0 Chrome\/117.0.0.0 Mobile Safari\/537.36 musical_ly_2023104030 JsSdk\/1.0 NetType\/WIFI Channel\/googleplay AppName\/musical_ly app_version\/31.4.3 ByteLocale\/pt-BR ByteFullLocale\/pt-BR Region\/BR Spark\/1.4.1.12-bugfix AppVersion\/31.4.3 BytedanceWebview\/d8a21c6","subs":[],"preland":"unknown","land":"velhorico\/mvr-app1","_id":45760}