{"subid":"6521cb8fd0596","time":1696713615,"ip":"177.55.224.206","country":"BR","os":"iOS","isp":"Tremnet Fibra","ua":"Mozilla\/5.0 (iPhone; CPU iPhone OS 16_1_2 like Mac OS X) AppleWebKit\/605.1.15 (KHTML  like Gecko) Mobile\/15E148 musical_ly_31.3.0 JsSdk\/2.0 NetType\/WIFI Channel\/App Store ByteLocale\/pt Region\/BR RevealType\/Dialog isDarkMode\/0 WKWebView\/1 BytedanceWebview\/d8a21c6 FalconTag\/C1822C5B-286D-4ED8-AF38-EEACF436D551","subs":[],"preland":"unknown","land":"velhorico\/mvr-app1","_id":47216}