{"subid":"64efc2d8d4dfe","time":1693434584,"ip":"131.161.134.94","country":"BR","os":"iOS","isp":"Sistema Oeste de Servicos LTDA","ua":"Mozilla\/5.0 (iPhone; CPU iPhone OS 16_1_1 like Mac OS X) AppleWebKit\/605.1.15 (KHTML  like Gecko) Mobile\/15E148 musical_ly_30.9.0 JsSdk\/2.0 NetType\/WIFI Channel\/App Store ByteLocale\/pt Region\/BR RevealType\/Dialog isDarkMode\/0 WKWebView\/1 BytedanceWebview\/d8a21c6 FalconTag\/D727BA18-17A7-42CC-A17D-040D4A208787","subs":[],"preland":"unknown","land":"avaliadoroferta\/1-3","_id":4799}