{"subid":"6521d247807ef","time":1696715335,"ip":"2804:1348:3781:f000:f84d:805:b406:aecb","country":"BR","os":"iOS","isp":"NEW TECNOLOGIA DA INFORMACAO LTDA - ME","ua":"Mozilla\/5.0 (iPhone; CPU iPhone OS 17_0_3 like Mac OS X) AppleWebKit\/605.1.15 (KHTML  like Gecko) Mobile\/15E148 musical_ly_31.3.0 JsSdk\/2.0 NetType\/WIFI Channel\/App Store ByteLocale\/pt Region\/BR isDarkMode\/0 WKWebView\/1 RevealType\/Dialog BytedanceWebview\/d8a21c6 FalconTag\/7DF39720-9083-4CEF-820C-3E2558B2C106","subs":[],"preland":"unknown","land":"velhorico\/mvr-app1","_id":48639}