{"subid":"64efc0c04f88a","time":1693436167,"ip":"2804:389:1047:de8b:29b8:7c67:a767:9bcd","country":"BR","os":"iOS","isp":"Claro SA","ua":"Mozilla\/5.0 (iPhone; CPU iPhone OS 16_3_1 like Mac OS X) AppleWebKit\/605.1.15 (KHTML  like Gecko) Mobile\/15E148 musical_ly_30.8.0 JsSdk\/2.0 NetType\/4G Channel\/App Store ByteLocale\/pt Region\/BR isDarkMode\/0 WKWebView\/1 RevealType\/Dialog BytedanceWebview\/d8a21c6 FalconTag\/7121C419-2173-4D8E-A8A1-D162A0102E51","subs":[],"preland":"unknown","land":"avaliadoroferta\/1-3","_id":4867}