{"subid":"6521dc0ea47cd","time":1696717838,"ip":"45.179.28.244","country":"BR","os":"iOS","isp":"MULTICOM INTERNET","ua":"Mozilla\/5.0 (iPhone; CPU iPhone OS 17_0_3 like Mac OS X) AppleWebKit\/605.1.15 (KHTML  like Gecko) Mobile\/15E148 musical_ly_31.3.0 JsSdk\/2.0 NetType\/WIFI Channel\/App Store ByteLocale\/en Region\/BR RevealType\/Dialog isDarkMode\/0 WKWebView\/1 BytedanceWebview\/d8a21c6 FalconTag\/6F318048-CD0A-4C8C-95D5-44059933A9ED","subs":[],"preland":"unknown","land":"velhorico\/mvr-app1","_id":50820}