{"subid":"6521e17170fee","time":1696719425,"ip":"179.189.168.55","country":"BR","os":"iOS","isp":"Rede Brasileira de Comunicacao SA","ua":"Mozilla\/5.0 (iPhone; CPU iPhone OS 16_6_1 like Mac OS X) AppleWebKit\/605.1.15 (KHTML  like Gecko) Mobile\/15E148 BytedanceWebview\/d8a21c6 musical_ly_31.3.0 JsSdk\/2.0 NetType\/WIFI Channel\/App Store ByteLocale\/pt Region\/BR FalconTag\/7CE404AF-32FC-444D-B614-3B2798BD4A52 TTP_H5_URLPROTOCOL","subs":[],"preland":"unknown","land":"velhorico\/mvr-app1","_id":51652}