{"subid":"6521e8b74ad02","time":1696721138,"ip":"45.172.68.30","country":"BR","os":"iOS","isp":"N-MULTIMIDIA TELECOMUNICACOES LTDA - ME","ua":"Mozilla\/5.0 (iPhone; CPU iPhone OS 16_1_2 like Mac OS X) AppleWebKit\/605.1.15 (KHTML  like Gecko) Mobile\/15E148 musical_ly_31.3.0 JsSdk\/2.0 NetType\/WIFI Channel\/App Store ByteLocale\/pt Region\/BR RevealType\/Dialog isDarkMode\/0 WKWebView\/1 BytedanceWebview\/d8a21c6 FalconTag\/7E92918A-E70F-4176-939E-8C9EDE06E268","subs":[],"preland":"unknown","land":"velhorico\/mvr-app1","_id":51695}