{"subid":"65220842628b8","time":1696729154,"ip":"45.160.182.136","country":"BR","os":"iOS","isp":"Conect Telecomunicacoes Ltda. ME","ua":"Mozilla\/5.0 (iPhone; CPU iPhone OS 15_7_9 like Mac OS X) AppleWebKit\/605.1.15 (KHTML  like Gecko) Mobile\/15E148 musical_ly_31.3.0 JsSdk\/2.0 NetType\/WIFI Channel\/App Store ByteLocale\/pt Region\/BR RevealType\/Dialog isDarkMode\/0 WKWebView\/1 BytedanceWebview\/d8a21c6 FalconTag\/8243EA81-2943-4C99-9A0F-86D6C2F519F9","subs":[],"preland":"unknown","land":"velhorico\/mvr-app1","_id":52632}