{"subid":"652208948a123","time":1696729236,"ip":"2804:8d4:34d:2920:a517:e8f1:f5f7:f2c7","country":"BR","os":"Android","isp":"VOCE TELECOMUNICACOES LTDA","ua":"Mozilla\/5.0 (Linux; Android 12; M2003J15SC Build\/SP1A.210812.016; wv) AppleWebKit\/537.36 (KHTML  like Gecko) Version\/4.0 Chrome\/117.0.0.0 Mobile Safari\/537.36 trill_2023104030 JsSdk\/1.0 NetType\/WIFI Channel\/googleplay AppName\/musical_ly app_version\/31.4.3 ByteLocale\/pt-BR ByteFullLocale\/pt-BR Region\/BR BytedanceWebview\/d8a21c6","subs":[],"preland":"unknown","land":"velhorico\/mvr-app1","_id":52692}