{"subid":"65220f936971d","time":1696731027,"ip":"187.106.42.81","country":"BR","os":"iOS","isp":"Claro NXT Telecomunicacoes Ltda","ua":"Mozilla\/5.0 (iPhone; CPU iPhone OS 15_7_1 like Mac OS X) AppleWebKit\/605.1.15 (KHTML  like Gecko) Mobile\/15E148 musical_ly_31.3.0 JsSdk\/2.0 NetType\/WIFI Channel\/App Store ByteLocale\/pt Region\/BR RevealType\/Dialog isDarkMode\/0 WKWebView\/1 BytedanceWebview\/d8a21c6 FalconTag\/7E872A52-91C1-4248-8AA8-F337C9D2F073","subs":[],"preland":"unknown","land":"velhorico\/mvr-app1","_id":53685}