{"subid":"65220fec8d667","time":1696731116,"ip":"2804:3358:2050:26b3:c580:10c0:816:9089","country":"BR","os":"iOS","isp":"Topnet Telecom Servicos LTDA ME","ua":"Mozilla\/5.0 (iPhone; CPU iPhone OS 16_7 like Mac OS X) AppleWebKit\/605.1.15 (KHTML  like Gecko) Mobile\/15E148 musical_ly_31.3.0 JsSdk\/2.0 NetType\/WIFI Channel\/App Store ByteLocale\/pt Region\/BR RevealType\/Dialog isDarkMode\/0 WKWebView\/1 BytedanceWebview\/d8a21c6 FalconTag\/DB6BBE6B-3766-4642-B443-73FE3F732D66","subs":[],"preland":"unknown","land":"velhorico\/mvr-app1","_id":53725}