{"subid":"65221a004e0d5","time":1696733696,"ip":"2804:a84:4006:6301:11bb:310b:14f0:2eab","country":"BR","os":"iOS","isp":"Windx Telecomunicacoes","ua":"Mozilla\/5.0 (iPhone; CPU iPhone OS 16_6_1 like Mac OS X) AppleWebKit\/605.1.15 (KHTML  like Gecko) Mobile\/15E148 musical_ly_31.2.0 JsSdk\/2.0 NetType\/WIFI Channel\/App Store ByteLocale\/pt Region\/BR RevealType\/Dialog isDarkMode\/0 WKWebView\/1 BytedanceWebview\/d8a21c6 FalconTag\/8857CB26-E33A-4FC6-B033-F599F67BF53B","subs":[],"preland":"unknown","land":"velhorico\/mvr-app1","_id":55118}