{"subid":"6522226bc60aa","time":1696735851,"ip":"2804:2140:1020:4270:56e:f6c9:a950:33ed","country":"BR","os":"iOS","isp":"Center Prestadora Servicos SC Ltda","ua":"Mozilla\/5.0 (iPhone; CPU iPhone OS 16_6_1 like Mac OS X) AppleWebKit\/605.1.15 (KHTML  like Gecko) Mobile\/15E148 BytedanceWebview\/d8a21c6 musical_ly_31.2.0 JsSdk\/2.0 NetType\/WIFI Channel\/App Store ByteLocale\/pt Region\/BR FalconTag\/6A2E4691-62B9-4822-95BC-FC2039F741A8 TTP_H5_URLPROTOCOL","subs":[],"preland":"unknown","land":"velhorico\/mvr-app1","_id":56151}