{"subid":"652223f96414d","time":1696736249,"ip":"186.227.65.222","country":"BR","os":"iOS","isp":"Avelino e Rodrigues LTDA","ua":"Mozilla\/5.0 (iPhone; CPU iPhone OS 16_3_1 like Mac OS X) AppleWebKit\/605.1.15 (KHTML  like Gecko) Mobile\/15E148 musical_ly_31.3.0 JsSdk\/2.0 NetType\/WIFI Channel\/App Store ByteLocale\/pt Region\/BR RevealType\/Dialog isDarkMode\/0 WKWebView\/1 BytedanceWebview\/d8a21c6 FalconTag\/387B6639-0F2C-4EE6-A00F-B766E4A455FF","subs":[],"preland":"unknown","land":"velhorico\/mvr-app1","_id":56259}