{"subid":"652227b30e450","time":1696737203,"ip":"2804:4f80:3e2c:e0a0:e4fe:8ba8:68c7:4506","country":"BR","os":"iOS","isp":"CNX TELECOMUNICACOES","ua":"Mozilla\/5.0 (iPhone; CPU iPhone OS 17_0_3 like Mac OS X) AppleWebKit\/605.1.15 (KHTML  like Gecko) Mobile\/15E148 musical_ly_31.3.0 JsSdk\/2.0 NetType\/WIFI Channel\/App Store ByteLocale\/pt Region\/BR RevealType\/Dialog isDarkMode\/0 WKWebView\/1 BytedanceWebview\/d8a21c6 FalconTag\/83069FAD-D55F-498C-8FAF-32BF24AF2C45","subs":[],"preland":"unknown","land":"velhorico\/mvr-app1","_id":56534}