{"subid":"64f0c64b6cda8","time":1693501003,"ip":"177.136.128.43","country":"BR","os":"Android","isp":"Predlink Rede de Telecomuniccoes Ltda","ua":"Mozilla\/5.0 (Linux; Android 10; moto e(7) Build\/QOFS30.569-83-18; wv) AppleWebKit\/537.36 (KHTML  like Gecko) Version\/4.0 Chrome\/116.0.0.0 Mobile Safari\/537.36 trill_2023100050 JsSdk\/1.0 NetType\/WIFI Channel\/googleplay AppName\/musical_ly app_version\/31.0.5 ByteLocale\/pt-BR ByteFullLocale\/pt-BR Region\/BR BytedanceWebview\/d8a21c6","subs":[],"preland":"unknown","land":"avaliador\/pv\/1-inicio","_id":5655}