{"subid":"6522283c3a71b","time":1696737340,"ip":"2804:d45:9e07:3200:b422:ae0a:b3e:660d","country":"BR","os":"iOS","isp":"Telemar Norte Leste S.A.","ua":"Mozilla\/5.0 (iPhone; CPU iPhone OS 16_6_1 like Mac OS X) AppleWebKit\/605.1.15 (KHTML  like Gecko) Mobile\/15E148 musical_ly_31.3.0 JsSdk\/2.0 NetType\/WIFI Channel\/App Store ByteLocale\/pt Region\/BR isDarkMode\/1 WKWebView\/1 RevealType\/Dialog BytedanceWebview\/d8a21c6 FalconTag\/376BFA13-A46A-403C-B2CF-539FAF5E50DE","subs":[],"preland":"unknown","land":"velhorico\/mvr-app1","_id":56583}