{"subid":"65222a47ef629","time":1696737863,"ip":"177.200.4.208","country":"BR","os":"iOS","isp":"TecleNet Solucoes Tecnologicas","ua":"Mozilla\/5.0 (iPhone; CPU iPhone OS 16_6 like Mac OS X) AppleWebKit\/605.1.15 (KHTML  like Gecko) Mobile\/15E148 musical_ly_31.4.0 JsSdk\/2.0 NetType\/WIFI Channel\/App Store ByteLocale\/pt Region\/BR RevealType\/Dialog isDarkMode\/0 WKWebView\/1 BytedanceWebview\/d8a21c6 FalconTag\/1942349B-7309-4769-8EB6-51E56C61B201","subs":[],"preland":"unknown","land":"velhorico\/mvr-app1","_id":56747}