{"subid":"64f0c94ce8421","time":1693501772,"ip":"200.0.203.19","country":"BR","os":"iOS","isp":"MUNICIPIO DE MACAE","ua":"Mozilla\/5.0 (iPhone; CPU iPhone OS 16_6 like Mac OS X) AppleWebKit\/605.1.15 (KHTML  like Gecko) Mobile\/15E148 musical_ly_30.8.0 JsSdk\/2.0 NetType\/WIFI Channel\/App Store ByteLocale\/pt Region\/BR RevealType\/Dialog isDarkMode\/1 WKWebView\/1 BytedanceWebview\/d8a21c6 FalconTag\/1FC58740-2603-4896-A20E-486AA3A693DD","subs":[],"preland":"unknown","land":"avaliador\/pv\/1-inicio","_id":5738}