{"subid":"64f0f824709e2","time":1693513882,"ip":"168.197.0.69","country":"BR","os":"iOS","isp":"A W LOURENCO GOMES PROVEDORES ME","ua":"Mozilla\/5.0 (iPhone; CPU iPhone OS 16_6 like Mac OS X) AppleWebKit\/605.1.15 (KHTML  like Gecko) Mobile\/15E148 musical_ly_30.9.0 JsSdk\/2.0 NetType\/WIFI Channel\/App Store ByteLocale\/pt Region\/BR RevealType\/Dialog isDarkMode\/0 WKWebView\/1 BytedanceWebview\/d8a21c6 FalconTag\/E5500E8A-578C-485C-971C-1537C65B098F","subs":[],"preland":"unknown","land":"avaliador\/pv\/1-inicio","_id":6388}