{"subid":"64f0fbdb63fb5","time":1693514715,"ip":"131.255.78.41","country":"BR","os":"iOS","isp":"CONECTMAIS COMUNICACOES LTDA","ua":"Mozilla\/5.0 (iPhone; CPU iPhone OS 16_6 like Mac OS X) AppleWebKit\/605.1.15 (KHTML  like Gecko) Mobile\/15E148 musical_ly_30.8.0 JsSdk\/2.0 NetType\/WIFI Channel\/App Store ByteLocale\/pt Region\/BR isDarkMode\/0 WKWebView\/1 RevealType\/Dialog BytedanceWebview\/d8a21c6 FalconTag\/27E0BB4F-221B-4C0E-9B59-69FF944B6900","subs":[],"preland":"unknown","land":"avaliador\/pv\/1-inicio","_id":6513}