{"subid":"64f1b07dbdbe0","time":1693560957,"ip":"191.55.81.21","country":"BR","os":"iOS","isp":"ALGAR TELECOM SA","ua":"Mozilla\/5.0 (iPhone; CPU iPhone OS 16_6 like Mac OS X) AppleWebKit\/605.1.15 (KHTML  like Gecko) Mobile\/15E148 musical_ly_30.8.0 JsSdk\/2.0 NetType\/WIFI Channel\/App Store ByteLocale\/pt Region\/BR isDarkMode\/1 WKWebView\/1 RevealType\/Dialog BytedanceWebview\/d8a21c6 FalconTag\/359A1527-B50E-46CD-AAB4-A4E52FC56EEB","subs":[],"preland":"unknown","land":"avaliador\/pv\/1-inicio","_id":7192}