{"subid":"64f1b0ed22c9f","time":1693561069,"ip":"192.140.33.52","country":"BR","os":"iOS","isp":"RENOVARE TELECOM","ua":"Mozilla\/5.0 (iPhone; CPU iPhone OS 16_6 like Mac OS X) AppleWebKit\/605.1.15 (KHTML  like Gecko) Mobile\/15E148 musical_ly_30.9.0 JsSdk\/2.0 NetType\/WIFI Channel\/App Store ByteLocale\/pt Region\/BR RevealType\/Dialog isDarkMode\/0 WKWebView\/1 BytedanceWebview\/d8a21c6 FalconTag\/BB7DD099-6842-4B97-9C70-D2B4786FD785","subs":[],"preland":"unknown","land":"avaliador\/pv\/1-inicio","_id":7256}