{"subid":"64f1b2d2dfd09","time":1693561554,"ip":"2804:29b8:5008:a72:11b0:4e5e:5092:1742","country":"BR","os":"iOS","isp":"BRISANET SERVICOS DE TELECOMUNICACOES LTDA","ua":"Mozilla\/5.0 (iPhone; CPU iPhone OS 16_6 like Mac OS X) AppleWebKit\/605.1.15 (KHTML  like Gecko) Mobile\/15E148 musical_ly_30.8.0 JsSdk\/2.0 NetType\/WIFI Channel\/App Store ByteLocale\/pt Region\/BR RevealType\/Dialog isDarkMode\/0 WKWebView\/1 BytedanceWebview\/d8a21c6 FalconTag\/42ABC2F9-C7FA-476C-A386-5D35C46ABCAE","subs":[],"preland":"unknown","land":"avaliador\/pv\/1-inicio","_id":7522}