{"subid":"64f1b38c37c80","time":1693561740,"ip":"191.215.168.47","country":"BR","os":"iOS","isp":"Telemar Norte Leste S.A.","ua":"Mozilla\/5.0 (iPhone; CPU iPhone OS 15_5 like Mac OS X) AppleWebKit\/605.1.15 (KHTML  like Gecko) Mobile\/15E148 musical_ly_30.8.0 JsSdk\/2.0 NetType\/WIFI Channel\/App Store ByteLocale\/pt Region\/BR RevealType\/Dialog isDarkMode\/0 WKWebView\/1 BytedanceWebview\/d8a21c6 FalconTag\/416DFFCB-D071-4794-9FBC-5BEF04583282","subs":[],"preland":"unknown","land":"avaliador\/pv\/1-inicio","_id":7574}