{"subid":"64f1b6918fc4d","time":1693562513,"ip":"2804:7f0:b1c1:3091:ccf0:27c1:9245:e787","country":"BR","os":"iOS","isp":"TELEFONICA BRASIL S.A","ua":"Mozilla\/5.0 (iPhone; CPU iPhone OS 16_6 like Mac OS X) AppleWebKit\/605.1.15 (KHTML  like Gecko) Mobile\/15E148 musical_ly_30.8.0 JsSdk\/2.0 NetType\/WIFI Channel\/App Store ByteLocale\/pt Region\/BR RevealType\/Dialog isDarkMode\/0 WKWebView\/1 BytedanceWebview\/d8a21c6 FalconTag\/560D4F94-3D7B-48A2-8044-F05377FDD426","subs":[],"preland":"unknown","land":"avaliador\/pv\/1-inicio","_id":7739}