{"subid":"64f1b7e54d756","time":1693562853,"ip":"2804:14c:a1:b6c2:e92b:a5a5:82b2:1ffb","country":"BR","os":"iOS","isp":"Claro NXT Telecomunicacoes Ltda","ua":"Mozilla\/5.0 (iPhone; CPU iPhone OS 16_6 like Mac OS X) AppleWebKit\/605.1.15 (KHTML  like Gecko) Mobile\/15E148 musical_ly_30.9.0 JsSdk\/2.0 NetType\/WIFI Channel\/App Store ByteLocale\/pt Region\/BR RevealType\/Dialog isDarkMode\/0 WKWebView\/1 BytedanceWebview\/d8a21c6 FalconTag\/73DCC434-4C5E-4261-A80E-67616FB84B0F","subs":[],"preland":"unknown","land":"avaliador\/pv\/1-inicio","_id":7785}