{"subid":"64f1bd199f401","time":1693564185,"ip":"187.36.168.50","country":"BR","os":"iOS","isp":"Claro NXT Telecomunicacoes Ltda","ua":"Mozilla\/5.0 (iPhone; CPU iPhone OS 15_6_1 like Mac OS X) AppleWebKit\/605.1.15 (KHTML  like Gecko) Mobile\/15E148 musical_ly_31.0.0 JsSdk\/2.0 NetType\/WIFI Channel\/App Store ByteLocale\/pt Region\/BR RevealType\/Dialog isDarkMode\/0 WKWebView\/1 BytedanceWebview\/d8a21c6 FalconTag\/96ABA99D-5702-409D-A9AB-DAC557A62032","subs":[],"preland":"unknown","land":"avaliador\/pv\/1-inicio","_id":7987}