{"subid":"64f1c0b440a82","time":1693565108,"ip":"2804:18:10f2:2bb5:51bf:e1f8:2ea:386f","country":"BR","os":"iOS","isp":"TELEFONICA BRASIL S.A","ua":"Mozilla\/5.0 (iPhone; CPU iPhone OS 16_6 like Mac OS X) AppleWebKit\/605.1.15 (KHTML  like Gecko) Mobile\/15E148 musical_ly_30.9.0 JsSdk\/2.0 NetType\/3G Channel\/App Store ByteLocale\/pt Region\/BR isDarkMode\/0 WKWebView\/1 RevealType\/Dialog BytedanceWebview\/d8a21c6 FalconTag\/732FC5FE-8DD8-447A-A2CD-A1F3915B0520","subs":[],"preland":"unknown","land":"avaliador\/pv\/1-inicio","_id":8098}