{"subid":"64f1c43a80af2","time":1693566010,"ip":"187.19.172.252","country":"BR","os":"iOS","isp":"BRISANET SERVICOS DE TELECOMUNICACOES LTDA","ua":"Mozilla\/5.0 (iPhone; CPU iPhone OS 16_5 like Mac OS X) AppleWebKit\/605.1.15 (KHTML  like Gecko) Mobile\/15E148 musical_ly_30.9.0 JsSdk\/2.0 NetType\/WIFI Channel\/App Store ByteLocale\/pt Region\/BR RevealType\/Dialog isDarkMode\/0 WKWebView\/1 BytedanceWebview\/d8a21c6 FalconTag\/0D61FA30-7056-40EA-B01D-489DB3E8D7AE","subs":[],"preland":"unknown","land":"avaliador\/pv\/1-inicio","_id":8279}