{"subid":"64f1c6dc44d8f","time":1693566684,"ip":"2804:7968:1cf:dc00:a8f6:b4ba:d7cf:9a37","country":"BR","os":"iOS","isp":"Brayo LTDA","ua":"Mozilla\/5.0 (iPhone; CPU iPhone OS 16_6 like Mac OS X) AppleWebKit\/605.1.15 (KHTML  like Gecko) Mobile\/15E148 musical_ly_30.8.0 JsSdk\/2.0 NetType\/WIFI Channel\/App Store ByteLocale\/pt Region\/BR RevealType\/Dialog isDarkMode\/0 WKWebView\/1 BytedanceWebview\/d8a21c6 FalconTag\/26400F76-0EAB-4E36-834C-4BCDC4D9F3E6","subs":[],"preland":"unknown","land":"avaliador\/pv\/1-inicio","_id":8354}