{"subid":"64f1c965e11d4","time":1693567333,"ip":"177.47.171.27","country":"BR","os":"iOS","isp":"WISP ICONECTA SERVICOS DE REDE LTDA","ua":"Mozilla\/5.0 (iPhone; CPU iPhone OS 16_6 like Mac OS X) AppleWebKit\/605.1.15 (KHTML  like Gecko) Mobile\/15E148 musical_ly_30.8.0 JsSdk\/2.0 NetType\/WIFI Channel\/App Store ByteLocale\/pt Region\/BR RevealType\/Dialog isDarkMode\/0 WKWebView\/1 BytedanceWebview\/d8a21c6 FalconTag\/D9EB6B3F-A169-4609-B41F-DC40D06AFC27","subs":[],"preland":"unknown","land":"avaliador\/pv\/1-inicio","_id":8422}