{"subid":"64f1cc47be8e2","time":1693568071,"ip":"177.39.94.104","country":"BR","os":"iOS","isp":"Sygo Internet","ua":"Mozilla\/5.0 (iPhone; CPU iPhone OS 16_6 like Mac OS X) AppleWebKit\/605.1.15 (KHTML  like Gecko) Mobile\/15E148 musical_ly_30.8.0 JsSdk\/2.0 NetType\/WIFI Channel\/App Store ByteLocale\/pt Region\/BR RevealType\/Dialog isDarkMode\/1 WKWebView\/1 BytedanceWebview\/d8a21c6 FalconTag\/434C7263-C4FA-43FD-A84C-D7DA516A46B3","subs":[],"preland":"unknown","land":"avaliador\/pv\/1-inicio","_id":8526}