{"subid":"64f1cde084b1d","time":1693568480,"ip":"170.245.124.142","country":"BR","os":"iOS","isp":"G & S INFORNET PROVEDOR DE INTERNET EIRELI","ua":"Mozilla\/5.0 (iPhone; CPU iPhone OS 16_6 like Mac OS X) AppleWebKit\/605.1.15 (KHTML  like Gecko) Mobile\/15E148 musical_ly_29.6.0 JsSdk\/2.0 NetType\/WIFI Channel\/App Store ByteLocale\/pt Region\/BR RevealType\/Dialog isDarkMode\/0 WKWebView\/1 BytedanceWebview\/d8a21c6 FalconTag\/FE0B2753-34AC-4450-9A38-CFB042ADB147","subs":[],"preland":"unknown","land":"avaliador\/pv\/1-inicio","_id":8590}