{"subid":"64f1d191173cf","time":1693569425,"ip":"45.70.159.231","country":"BR","os":"iOS","isp":"MAXBR COMERCIO E PRESTACAO DE SERVICOS LTDA - ME","ua":"Mozilla\/5.0 (iPhone; CPU iPhone OS 16_6 like Mac OS X) AppleWebKit\/605.1.15 (KHTML  like Gecko) Mobile\/15E148 musical_ly_30.8.0 JsSdk\/2.0 NetType\/WIFI Channel\/App Store ByteLocale\/pt Region\/BR RevealType\/Dialog isDarkMode\/0 WKWebView\/1 BytedanceWebview\/d8a21c6 FalconTag\/2597DB68-7D6E-4A5D-974E-57F1F8ACD2DC","subs":[],"preland":"unknown","land":"avaliador\/pv\/1-inicio","_id":8695}