{"subid":"64f1d5f8191e1","time":1693570552,"ip":"191.241.148.140","country":"BR","os":"iOS","isp":"SATURNO COMUNICACOES LTDA","ua":"Mozilla\/5.0 (iPhone; CPU iPhone OS 16_6 like Mac OS X) AppleWebKit\/605.1.15 (KHTML  like Gecko) Mobile\/15E148 musical_ly_30.8.0 JsSdk\/2.0 NetType\/WIFI Channel\/App Store ByteLocale\/pt Region\/BR RevealType\/Dialog isDarkMode\/0 WKWebView\/1 BytedanceWebview\/d8a21c6 FalconTag\/612168B8-2033-4A41-878B-24B8BCAA58CC","subs":[],"preland":"unknown","land":"avaliador\/pv\/1-inicio","_id":8824}